hugolibs/Funciones.py
hugolibs/__init__.py
hugolibs-0.3.8.dist-info/LICENSE.txt
hugolibs-0.3.8.dist-info/METADATA
hugolibs-0.3.8.dist-info/WHEEL
hugolibs-0.3.8.dist-info/top_level.txt
hugolibs-0.3.8.dist-info/RECORD
