Metadata-Version: 2.1
Name: hugolibs
Version: 0.3.8
Summary: Librería con funciones básicas en español
Home-page: https://github.com/Hugetrone12
Author: Hugo Andión Álvarez
Author-email: hugoandionalvarez@gmail.com
License: MIT
Platform: UNKNOWN
License-File: LICENSE.txt
